petstore_sdk/__init__.py
petstore_sdk/sdk.py
petstore_sdk/hooks/__init__.py
petstore_sdk/hooks/hook.py
petstore_sdk/models/__init__.py
petstore_sdk/models/base.py
petstore_sdk/models/pet.py
petstore_sdk/models/utils/cast_models.py
petstore_sdk/models/utils/json_map.py
petstore_sdk/net/__init__.py
petstore_sdk/net/environment/__init__.py
petstore_sdk/net/environment/environment.py
petstore_sdk/net/headers/__init__.py
petstore_sdk/net/headers/access_token_auth.py
petstore_sdk/net/headers/base_header.py
petstore_sdk/net/request_chain/__init__.py
petstore_sdk/net/request_chain/request_chain.py
petstore_sdk/net/request_chain/handlers/__init__.py
petstore_sdk/net/request_chain/handlers/base_handler.py
petstore_sdk/net/request_chain/handlers/hook_handler.py
petstore_sdk/net/request_chain/handlers/http_handler.py
petstore_sdk/net/request_chain/handlers/retry_handler.py
petstore_sdk/net/transport/__init__.py
petstore_sdk/net/transport/request.py
petstore_sdk/net/transport/request_error.py
petstore_sdk/net/transport/response.py
petstore_sdk/net/transport/serializer.py
petstore_sdk/net/transport/utils.py
petstore_sdk/services/__init__.py
petstore_sdk/services/pets.py
petstore_sdk/services/utils/base_service.py
petstore_sdk/services/utils/default_headers.py
petstore_sdk/services/utils/validator.py
petstore_pypi-2.0.6.dist-info/LICENSE
petstore_pypi-2.0.6.dist-info/METADATA
petstore_pypi-2.0.6.dist-info/WHEEL
petstore_pypi-2.0.6.dist-info/top_level.txt
petstore_pypi-2.0.6.dist-info/RECORD
