Metadata-Version: 2.1
Name: petstore-pypi
Version: 2.0.6
License: MIT
Requires-Python: >=3.7
License-File: LICENSE
Requires-Dist: requests >=2.31.0
